jupyterlab_dotscience_backend/__init__.py
jupyterlab_dotscience_backend-0.2.30.dist-info/METADATA
jupyterlab_dotscience_backend-0.2.30.dist-info/WHEEL
jupyterlab_dotscience_backend-0.2.30.dist-info/top_level.txt
jupyterlab_dotscience_backend-0.2.30.dist-info/RECORD
