Metadata-Version: 2.1
Name: jupyterlab-dotscience-backend
Version: 0.2.30
Summary: Backend component for dotmesh
Home-page: https://github.com/dotmesh-io/jupyterlab-plugin
Author: dotmesh
Author-email: luke@dotmesh.com
License: UNKNOWN
Platform: UNKNOWN
Classifier: Programming Language :: Python :: 3
Classifier: License :: OSI Approved :: MIT License
Classifier: Operating System :: OS Independent
Requires-Dist: datadots-api (>=0.2.4)
